{"cameraMode":{"drawMode":0,"name":"Shaded","section":"Shading Mode"},"sceneLighting":true,"audioPlay":false,"sceneViewState":{"m_AlwaysRefresh":false,"showFog":true,"showSkybox":true,"showFlares":true,"showImageEffects":true,"showParticleSystems":true,"showVisualEffectGraphs":true,"m_FxEnabled":true},"in2DMode":false,"pivot":{"x":-2.4505538940429689,"y":2.72592830657959,"z":11.20722770690918},"rotation":{"x":-0.16146798431873322,"y":0.5030292868614197,"z":-0.09626655280590058,"w":-0.8442163467407227},"size":0.40609508752822878,"orthographic":false}